cdc/__init__.py
cdc_cluster-0.1.1.dist-info/METADATA
cdc_cluster-0.1.1.dist-info/WHEEL
cdc_cluster-0.1.1.dist-info/top_level.txt
cdc_cluster-0.1.1.dist-info/RECORD
