Metadata-Version: 2.1
Name: cdc-cluster
Version: 0.1.1
Summary: A novel Clustering algorithm by measuring Direction Centrality (CDC) locally. It adopts a density-independent metric based on the distribution of K-nearest neighbors (KNNs) to distinguish between internal and boundary points. The boundary points generate enclosed cages to bind the connections of internal points.
Author-email: pdh <pengdh@whu.edu.cn>
Project-URL: Homepage, https://github.com/ZPGuiGroupWhu/CDC-pkg
Project-URL: Repository, https://github.com/ZPGuiGroupWhu/CDC-pkg.git
Project-URL: Bug Tracker, https://github.com/ZPGuiGroupWhu/CDC-pkg/issues
Keywords: clustering,centrality,boundary detection
Classifier: Development Status :: 3 - Alpha
Classifier: Intended Audience :: Science/Research
Classifier: Intended Audience :: Developers
Classifier: License :: OSI Approved :: MIT License
Classifier: Operating System :: OS Independent
Classifier: Programming Language :: Python :: 3
Classifier: Programming Language :: Python :: 3.8
Classifier: Programming Language :: Python :: 3.9
Classifier: Programming Language :: Python :: 3.10
Classifier: Programming Language :: Python :: 3.11
Classifier: Programming Language :: Python :: 3.12
Requires-Python: >=3.8
Requires-Dist: scikit-learn>=1.3.2
